prompts/__init__.py
prompts/dynamic.py
prompts/ensemble.py
prompts/exceptions.py
prompts/schemas.py
prompts/turbo.py
prompts/utils.py
AIPrompts-0.5.6.dist-info/METADATA
AIPrompts-0.5.6.dist-info/WHEEL
AIPrompts-0.5.6.dist-info/top_level.txt
AIPrompts-0.5.6.dist-info/RECORD
