Metadata-Version: 2.1
Name: AIPrompts
Version: 0.5.6
Summary: Create and parse prompts for large language models.
Home-page: https://github.com/TeiaLabs/prompts
Author: Teialabs
Author-email: jonatas@teialabs.com
Keywords: prompt openai teialabs gpt3
Requires-Python: >=3.10
Requires-Dist: pyaml
Requires-Dist: pytest
Requires-Dist: pydantic
